{
  "generator-jhipster": {
    "promptValues": {
      "packageName": "com.gpbdo.store",
      "nativeLanguage": "en"
    },
    "jhipsterVersion": "4.14.1",
    "baseName": "store",
    "packageName": "com.gpbdo.store",
    "packageFolder": "com/gpbdo/store",
    "serverPort": "8081",
    "authenticationType": "jwt",
    "cacheProvider": "hazelcast",
    "enableHibernateCache": false,
    "websocket": false,
    "databaseType": "mongodb",
    "devDatabaseType": "mongodb",
    "prodDatabaseType": "mongodb",
    "searchEngine": false,
    "messageBroker": false,
    "serviceDiscoveryType": "eureka",
    "buildTool": "maven",
    "enableSocialSignIn": false,
    "enableSwaggerCodegen": false,
    "jwtSecretKey": "745e3b02b2c354daa26a72b07106220bd328b5f3",
    "enableTranslation": true,
    "applicationType": "microservice",
    "testFrameworks": [
      "gatling"
    ],
    "jhiPrefix": "jhi",
    "nativeLanguage": "en",
    "languages": [
      "en",
      "es"
    ],
    "clientPackageManager": "yarn",
    "skipClient": true,
    "skipUserManagement": true
  }
}